Workbook

Sheet Свод
A1: Проект: | B1: AI Day для педагогов
A2: Заказчик: | B2: АО «Просветительский Холдинг»
A3: Дата составления расчёта: | B3: 18.06.2026
A5: РАЗБИВКА СТАРТОВОЙ ЦЕНЫ
A6: ФОТ (фонд оплаты труда) | B6: ='Доп_расходы'!B2
A7: ТМЦ (товарно-материальные ценности) | B7: ='Доп_расходы'!B3
A8: Прямые затраты (ФОТ + ТМЦ) | B8: ='Доп_расходы'!B4
A9: Накладные расходы (20%) | B9: ='Доп_расходы'!B5
A10: Прибыль (5%) | B10: ='Доп_расходы'!B6
A11: Итого без НДС | B11: ='Доп_расходы'!B7
A12: НДС (20%) | B12: ='Доп_расходы'!B8
A13: ИТОГОВАЯ СТАРТОВАЯ ЦЕНА КОНТРАКТА | B13: ='Доп_расходы'!B9
A16: ПРИМЕНЁННАЯ МЕТОДИКА
A17: Метод расчёта | B17: Затратный метод: прямые затраты + накладные расходы + прибыль + НДС; Корпоративный стандарт kpop, разд. II.
A18: Применённый порог КВ, % | B18: 20%; применён более строгий порог из письма Минпросвещения от 20.11.2025 № 07-1234/2025, п. 2.
A19: Источник ставок ФОТ | B19: regulations/okved-rates-mos-ru.csv, выгрузка 01.09.2026; Корпоративный стандарт kpop, разд. IV.
A20: Лимит накладных расходов, % от прямых | B20: 20%; Корпоративный стандарт kpop, разд. VI.
A21: Лимит прибыли, % от прямых | B21: 5%; Корпоративный стандарт kpop, разд. VI.
A22: Найденные расхождения нормативки | B22: Расхождение: kpop допускает КВ до 33%, письмо Минпросвещения рекомендует 20%; выбран 20% как более строгий для бюджетного обоснования.
A23: Скриншоты КП проверены оператором (по п. 5.3) | B23: Морозова И.А., 18.06.2026; проверка скриншотов КП по п. 5.3 корпоративного стандарта.

Sheet Роли
A1: специалист | B1: количество_человек | C1: человеко_дни | D1: часов_в_день | E1: человеко_часы | F1: okved_code | G1: ставка_руб_час | H1: ФОТ_руб
A2: Руководитель проекта | B2: 1 | C2: 5 | D2: 8 | E2: =B2*C2*D2 | F2: 82.3 | G2: =IFERROR(VLOOKUP(F2, 'ОКВЭДы'!$A$2:$C$26, 3, FALSE), "") | H2: =IFERROR(E2*G2, "")
A3: Координатор регистрации и участников | B3: 2 | C3: 3 | D3: 8 | E3: =B3*C3*D3 | F3: 82.3 | G3: =IFERROR(VLOOKUP(F3, 'ОКВЭДы'!$A$2:$C$26, 3, FALSE), "") | H3: =IFERROR(E3*G3, "")
A4: Технический координатор площадки | B4: 1 | C4: 4 | D4: 8 | E4: =B4*C4*D4 | F4: 82.3 | G4: =IFERROR(VLOOKUP(F4, 'ОКВЭДы'!$A$2:$C$26, 3, FALSE), "") | H4: =IFERROR(E4*G4, "")
A5: Специалист по AV и звуку | B5: 1 | C5: 4 | D5: 8 | E5: =B5*C5*D5 | F5: 59.2 | G5: =IFERROR(VLOOKUP(F5, 'ОКВЭДы'!$A$2:$C$26, 3, FALSE), "") | H5: =IFERROR(E5*G5, "")
A6: Дизайнер навигации и печатных материалов | B6: 1 | C6: 3 | D6: 8 | E6: =B6*C6*D6 | F6: 74.1 | G6: =IFERROR(VLOOKUP(F6, 'ОКВЭДы'!$A$2:$C$26, 3, FALSE), "") | H6: =IFERROR(E6*G6, "")
A7: Специалист по закупкам и КП | B7: 1 | C7: 3 | D7: 8 | E7: =B7*C7*D7 | F7: 73.2 | G7: =IFERROR(VLOOKUP(F7, 'ОКВЭДы'!$A$2:$C$26, 3, FALSE), "") | H7: =IFERROR(E7*G7, "")
A8: Методист программы форума | B8: 1 | C8: 4 | D8: 8 | E8: =B8*C8*D8 | F8: 85 | G8: =IFERROR(VLOOKUP(F8, 'ОКВЭДы'!$A$2:$C$26, 3, FALSE), "") | H8: =IFERROR(E8*G8, "")
A9: Администратор площадки | B9: 1 | C9: 3 | D9: 8 | E9: =B9*C9*D9 | F9: 82 | G9: =IFERROR(VLOOKUP(F9, 'ОКВЭДы'!$A$2:$C$26, 3, FALSE), "") | H9: =IFERROR(E9*G9, "")
E10: =B10*C10*D10 | G10: =IFERROR(VLOOKUP(F10, 'ОКВЭДы'!$A$2:$C$26, 3, FALSE), "") | H10: =IFERROR(E10*G10, "")
E11: =B11*C11*D11 | G11: =IFERROR(VLOOKUP(F11, 'ОКВЭДы'!$A$2:$C$26, 3, FALSE), "") | H11: =IFERROR(E11*G11, "")
E12: =B12*C12*D12 | G12: =IFERROR(VLOOKUP(F12, 'ОКВЭДы'!$A$2:$C$26, 3, FALSE), "") | H12: =IFERROR(E12*G12, "")
E13: =B13*C13*D13 | G13: =IFERROR(VLOOKUP(F13, 'ОКВЭДы'!$A$2:$C$26, 3, FALSE), "") | H13: =IFERROR(E13*G13, "")
E14: =B14*C14*D14 | G14: =IFERROR(VLOOKUP(F14, 'ОКВЭДы'!$A$2:$C$26, 3, FALSE), "") | H14: =IFERROR(E14*G14, "")
E15: =B15*C15*D15 | G15: =IFERROR(VLOOKUP(F15, 'ОКВЭДы'!$A$2:$C$26, 3, FALSE), "") | H15: =IFERROR(E15*G15, "")
E16: =B16*C16*D16 | G16: =IFERROR(VLOOKUP(F16, 'ОКВЭДы'!$A$2:$C$26, 3, FALSE), "") | H16: =IFERROR(E16*G16, "")
E17: =B17*C17*D17 | G17: =IFERROR(VLOOKUP(F17, 'ОКВЭДы'!$A$2:$C$26, 3, FALSE), "") | H17: =IFERROR(E17*G17, "")
E18: =B18*C18*D18 | G18: =IFERROR(VLOOKUP(F18, 'ОКВЭДы'!$A$2:$C$26, 3, FALSE), "") | H18: =IFERROR(E18*G18, "")
E19: =B19*C19*D19 | G19: =IFERROR(VLOOKUP(F19, 'ОКВЭДы'!$A$2:$C$26, 3, FALSE), "") | H19: =IFERROR(E19*G19, "")
E20: =B20*C20*D20 | G20: =IFERROR(VLOOKUP(F20, 'ОКВЭДы'!$A$2:$C$26, 3, FALSE), "") | H20: =IFERROR(E20*G20, "")
E21: =B21*C21*D21 | G21: =IFERROR(VLOOKUP(F21, 'ОКВЭДы'!$A$2:$C$26, 3, FALSE), "") | H21: =IFERROR(E21*G21, "")
A23: ИТОГО ФОТ: | H23: =SUM(H2:H21)

Sheet ТМЦ
A1: позиция | B1: ед_изм | C1: количество | D1: средняя_цена_руб | E1: сумма_руб
A2: Аренда проводных микрофонов с подставками | B2: шт. на 3 дня | C2: 5 | D2: ='Анализ_рынка'!H2 | E2: =IFERROR(C2*D2, "")
A3: Аренда активных акустических колонок | B3: шт. на 3 дня | C3: 4 | D3: ='Анализ_рынка'!H3 | E3: =IFERROR(C3*D3, "")
A4: Печать программы форума А5, 4 полосы, тираж 300 | B4: тираж | C4: 1 | D4: ='Анализ_рынка'!H4 | E4: =IFERROR(C4*D4, "")
A5: Пластиковые бейджи 90x60 мм с лентой | B5: шт. | C5: 300 | D5: ='Анализ_рынка'!H5 | E5: =IFERROR(C5*D5, "")
A6: Брендированные блокноты А5 с ручкой | B6: комплект | C6: 300 | D6: ='Анализ_рынка'!H6 | E6: =IFERROR(C6*D6, "")
A7: Печать плакатов А1 для навигации | B7: шт. | C7: 10 | D7: ='Анализ_рынка'!H7 | E7: =IFERROR(C7*D7, "")
E8: =IFERROR(C8*D8, "")
E9: =IFERROR(C9*D9, "")
E10: =IFERROR(C10*D10, "")
E11: =IFERROR(C11*D11, "")
A14: ИТОГО ТМЦ: | E14: =SUM(E2:E11)

Sheet Анализ_рынка
A1: позиция | B1: КП-1, ₽ | C1: скрин КП-1 | D1: КП-2, ₽ | E1: скрин КП-2 | F1: КП-3, ₽ | G1: скрин КП-3 | H1: СРЕДНЕЕ | I1: СТАНДОТКЛОН | J1: КВ, % | K1: проверка ≤ 20% | M1: Проверка источников ценовой информации
A2: Аренда проводных микрофонов с подставками | B2: 2100 | C2: offers/01_microphones/kp-1.png | D2: 1600 | E2: offers/01_microphones/kp-2.png | F2: 2250 | G2: offers/01_microphones/kp-3.png | H2: =IFERROR(AVERAGE(B2,D2,F2), "") | I2: =IFERROR(STDEV(B2,D2,F2), "") | J2: =IFERROR(I2/H2*100, "") | K2: =IF(J2="", "", IF(J2<=20, "OK", "превышение")) | M2: позиция | N2: КП | O2: URL | P2: цена | Q2: статус | R2: примечание
A3: Аренда активных акустических колонок | B3: 9000 | C3: offers/02_speakers/kp-1.png | D3: 10500 | E3: offers/02_speakers/kp-2.png | F3: 9375 | G3: offers/02_speakers/kp-3.png | H3: =IFERROR(AVERAGE(B3,D3,F3), "") | I3: =IFERROR(STDEV(B3,D3,F3), "") | J3: =IFERROR(I3/H3*100, "") | K3: =IF(J3="", "", IF(J3<=20, "OK", "превышение")) | M3: Аренда проводных микрофонов с подставками | N3: КП-1 | O3: https://rl-tech.ru/arenda-zvukovogo-oborudovaniya/arenda-microphona/ | P3: 2100 | Q3: одобрено | R3: проводной микрофон со стойкой, 3 дня: 1500 + 300 + 300
A4: Печать программы форума А5, 4 полосы, тираж 300 | B4: 3000 | C4: offers/03_programs_a5/kp-1.png | D4: 2610 | E4: offers/03_programs_a5/kp-2.png | F4: 2100 | G4: offers/03_programs_a5/kp-3.png | H4: =IFERROR(AVERAGE(B4,D4,F4), "") | I4: =IFERROR(STDEV(B4,D4,F4), "") | J4: =IFERROR(I4/H4*100, "") | K4: =IF(J4="", "", IF(J4<=20, "OK", "превышение")) | M4: Аренда проводных микрофонов с подставками | N4: КП-2 | O4: https://lsmedia-sound.ru/microfone | P4: 1600 | Q4: одобрено | R4: Shure SM58, 500 руб/сут, 3 дня + сопоставимая стойка/базовая коммутация; приведено к комплекту ТЗ
A5: Пластиковые бейджи 90x60 мм с лентой | B5: 47 | C5: offers/04_badges/kp-1.png | D5: 42 | E5: offers/04_badges/kp-2.png | F5: 39 | G5: offers/04_badges/kp-3.png | H5: =IFERROR(AVERAGE(B5,D5,F5), "") | I5: =IFERROR(STDEV(B5,D5,F5), "") | J5: =IFERROR(I5/H5*100, "") | K5: =IF(J5="", "", IF(J5<=20, "OK", "превышение")) | M5: Аренда проводных микрофонов с подставками | N5: КП-3 | O5: https://www.mistervo.ru/catalog/arenda_zvuka/arenda_microphonov-arenda-megafonov/shnurovye-mikrofony-shure-sm-58.html | P5: 2250 | Q5: одобрено | R5: Shure SM58, 750 руб/сут, 3 дня
A6: Брендированные блокноты А5 с ручкой | B6: 466.95 | C6: offers/05_notebooks_pens/kp-1.png | D6: 454.33 | E6: offers/05_notebooks_pens/kp-2.png | F6: 521 | G6: offers/05_notebooks_pens/kp-3.png | H6: =IFERROR(AVERAGE(B6,D6,F6), "") | I6: =IFERROR(STDEV(B6,D6,F6), "") | J6: =IFERROR(I6/H6*100, "") | K6: =IF(J6="", "", IF(J6<=20, "OK", "превышение")) | M6: Аренда активных акустических колонок | N6: КП-1 | O6: https://profiprazdnik.ru/catalog/arenda-zvuka/ | P6: 9000 | Q6: одобрено | R6: Mackie SRM 450, 3000 руб/сут, 3 дня
A7: Печать плакатов А1 для навигации | B7: 198 | C7: offers/06_posters_a1/kp-1.png | D7: 250 | E7: offers/06_posters_a1/kp-2.png | F7: 199 | G7: offers/06_posters_a1/kp-3.png | H7: =IFERROR(AVERAGE(B7,D7,F7), "") | I7: =IFERROR(STDEV(B7,D7,F7), "") | J7: =IFERROR(I7/H7*100, "") | K7: =IF(J7="", "", IF(J7<=20, "OK", "превышение")) | M7: Аренда активных акустических колонок | N7: КП-2 | O7: https://www.mistervo.ru/catalog/arenda_zvuka/arenda-zvukovogo-oborudovaniya-v-moskve/arenda-qsc-k12.2.html | P7: 10500 | Q7: одобрено | R7: QSC K12.2, 3500 руб/сут, 3 дня
H8: =IFERROR(AVERAGE(B8,D8,F8), "") | I8: =IFERROR(STDEV(B8,D8,F8), "") | J8: =IFERROR(I8/H8*100, "") | K8: =IF(J8="", "", IF(J8<=20, "OK", "превышение")) | M8: Аренда активных акустических колонок | N8: КП-3 | O8: https://www.rentalservice.moscow/prokat/zvukovoe-oborudovanie/aktivnie-sistemi | P8: 9375 | Q8: одобрено | R8: активная акустическая система, 3125 руб/сут, 3 дня
H9: =IFERROR(AVERAGE(B9,D9,F9), "") | I9: =IFERROR(STDEV(B9,D9,F9), "") | J9: =IFERROR(I9/H9*100, "") | K9: =IF(J9="", "", IF(J9<=20, "OK", "превышение")) | M9: Печать программы форума А5, 4 полосы, тираж 300 | N9: КП-1 | O9: https://poligrafiya-moscow.ru/pechat-listovok-a5.html | P9: 3000 | Q9: одобрено | R9: А5 4+4, тираж 300
H10: =IFERROR(AVERAGE(B10,D10,F10), "") | I10: =IFERROR(STDEV(B10,D10,F10), "") | J10: =IFERROR(I10/H10*100, "") | K10: =IF(J10="", "", IF(J10<=20, "OK", "превышение")) | M10: Печать программы форума А5, 4 полосы, тираж 300 | N10: КП-2 | O10: https://kopirka.ru/uslugi/operativnaya-poligrafiya/listovki/ | P10: 2610 | Q10: одобрено | R10: листовка А5, тираж 300
H11: =IFERROR(AVERAGE(B11,D11,F11), "") | I11: =IFERROR(STDEV(B11,D11,F11), "") | J11: =IFERROR(I11/H11*100, "") | K11: =IF(J11="", "", IF(J11<=20, "OK", "превышение")) | M11: Печать программы форума А5, 4 полосы, тираж 300 | N11: КП-3 | O11: https://www.galla-m.ru/poligrafiya/listovki/listovki-a5/ | P11: 2100 | Q11: одобрено | R11: листовки А5, тираж 300
M12: Пластиковые бейджи 90x60 мм с лентой | N12: КП-1 | O12: https://www.bholder.ru/izgotovlenie-bejdzhej/bejdzhi-dlya-meropriyatij | P12: 47 | Q12: одобрено | R12: пластиковый бейдж с лентой, цена за шт при 300+
M13: Пластиковые бейджи 90x60 мм с лентой | N13: КП-2 | O13: https://www.badgeshop.ru/catalog/materials/plastic/ | P13: 42 | Q13: одобрено | R13: пластиковый бейдж 90x60, цена за шт
M14: Пластиковые бейджи 90x60 мм с лентой | N14: КП-3 | O14: https://shnurok.ru/product/plastikovyy-beydzh-razmerom-90x60mm/ | P14: 39 | Q14: одобрено | R14: пластиковый бейдж 90x60, цена за шт при 300
M15: Брендированные блокноты А5 с ручкой | N15: КП-1 | O15: https://www.adverti.ru/diary/notebooks/sort_product-bloknot_s_ruchkoj/ | P15: 466.95 | Q15: одобрено | R15: блокнот А5 Toledo M с ручкой, цена за комплект
M16: Брендированные блокноты А5 с ручкой | N16: КП-2 | O16: https://prstyle.ru/catalog/ezhednevniki-i-planingi/bloknoty-s-ruchkoy/ | P16: 454.33 | Q16: одобрено | R16: блокнот с ручкой А5 Write and stick, цена за комплект
M17: Брендированные блокноты А5 с ручкой | N17: КП-3 | O17: https://www.adverti.ru/diary/notebooks/sort_product-bloknot_s_ruchkoj/ | P17: 521 | Q17: одобрено | R17: блокнот с ручкой Makron A5, цена за комплект
M18: Печать плакатов А1 для навигации | N18: КП-1 | O18: https://moscowyard.ru/shirokoformatnaya-pechat/pechat-plakaty-a1 | P18: 198 | Q18: одобрено | R18: плакат А1, цена за шт
M19: Печать плакатов А1 для навигации | N19: КП-2 | O19: https://tprint.ru/pechat-plakatov-a1/ | P19: 250 | Q19: одобрено | R19: плакат А1 обычная бумага, цена за шт
M20: Печать плакатов А1 для навигации | N20: КП-3 | O20: https://pappermint.ru/plakati-pechat/a1 | P20: 199 | Q20: одобрено | R20: плакат А1, 10 шт к оплате 1990, цена за шт

Sheet ОКВЭДы
A1: okved_code | B1: название | C1: ставка_руб_час | E1: Скопируй сюда только использованные в проекте строки из файла regulations/okved-rates-mos-ru.csv
A2: 59.2 | B2: Деятельность в области звукозаписи и издания музыкальных произведений | C2: 1405
A3: 73.2 | B3: Исследование конъюнктуры рынка и общественного мнения | C3: 2890
A4: 74.1 | B4: Деятельность специализированная в области дизайна | C4: 1490
A5: 82 | B5: Деятельность административно-хозяйственная и вспомогательная | C5: 1485
A6: 82.3 | B6: Деятельность по организации конференций и выставок | C6: 2185
A7: 85 | B7: Образование | C7: 1130

Sheet Доп_расходы
A1: параметр | B1: значение
A2: ФОТ (из листа Роли) | B2: ='Роли'!H23
A3: ТМЦ (из листа ТМЦ) | B3: ='ТМЦ'!E14
A4: Прямые затраты | B4: =B2+B3
A5: Накладные расходы (20% от прямых) | B5: =B4*0.2
A6: Прибыль (5% от прямых) | B6: =B4*0.05
A7: Итого без НДС | B7: =B4+B5+B6
A8: НДС (20%, сверху) | B8: =B7*0.2
A9: ИТОГОВАЯ СТАРТОВАЯ ЦЕНА | B9: =B7+B8
